LICENSE
nonefn/__init__.py
nonefn-0.1.0.dist-info/LICENSE
nonefn-0.1.0.dist-info/WHEEL
nonefn-0.1.0.dist-info/METADATA
nonefn-0.1.0.dist-info/RECORD
