Metadata-Version: 2.1
Name: nonefn
Version: 0.1.0
Summary: Some usefull functions you don't want to write again
Home-page: https://github.com/hglong16/nonefn
License: MIT
Keywords: nonefn,none,fn,function,python
Author: hglong16
Author-email: intihad.vuong@gmail.com
Requires-Python: >=3.9,<4.0
Classifier: Environment :: Console
Classifier: License :: OSI Approved :: MIT License
Classifier: Operating System :: OS Independent
Classifier: Programming Language :: Python :: 3
Classifier: Programming Language :: Python :: 3.9
Classifier: Programming Language :: Python :: 3.10
Classifier: Programming Language :: Python :: 3.11
Classifier: Topic :: Software Development :: Documentation
Classifier: Topic :: Software Development :: Libraries :: Python Modules
Classifier: Topic :: Software Development :: Quality Assurance
Project-URL: Repository, https://github.com/hglong16/nonefn
